{
  "project_info": {
    "project_number": "453591806698",
    "project_id": "neurocare-connect-44235",
    "storage_bucket": "neurocare-connect-44235.firebasestorage.app"
  },
  "client": [
    {
      "client_info": {
        "mobilesdk_app_id": "1:453591806698:android:710b5ef00868971643dd93",
        "android_client_info": {
          "package_name": "com.neurocare.connect"
        }
      },
      "oauth_client": [],
      "api_key": [
        {
          "current_key": "AIzaSyA5LepnbmgZ5Jk7oCnF_6wOAuIXCgkJEYE"
        }
      ],
      "services": {
        "appinvite_service": {
          "other_platform_oauth_client": []
        }
      }
    },
    {
      "client_info": {
        "mobilesdk_app_id": "1:453591806698:android:5253eab3ba7cd97343dd93",
        "android_client_info": {
          "package_name": "com.neurocare.connect"
        }
      },
      "oauth_client": [],
      "api_key": [
        {
          "current_key": "AIzaSyA5LepnbmgZ5Jk7oCnF_6wOAuIXCgkJEYE"
        }
      ],
      "services": {
        "appinvite_service": {
          "other_platform_oauth_client": []
        }
      }
    }
  ],
  "configuration_version": "1"
}